ainative/__init__.py
ainative/agent_coordination.py
ainative/agent_identity_system.py
ainative/agent_learning.py
ainative/agent_orchestration.py
ainative/agent_state.py
ainative/auth.py
ainative/cli.py
ainative/client.py
ainative/exceptions.py
ainative/agent_swarm/__init__.py
ainative/cli_utils/__init__.py
ainative/cli_utils/diff.py
ainative/cli_utils/formatters.py
ainative/commands/__init__.py
ainative/commands/agents.py
ainative/commands/coordination.py
ainative/commands/inspect.py
ainative/commands/learning.py
ainative/commands/local.py
ainative/commands/state.py
ainative/commands/swarm.py
ainative/commands/sync.py
ainative/commands/tasks.py
ainative/zerodb/__init__.py
ainative/zerodb/analytics.py
ainative/zerodb/memory.py
ainative/zerodb/projects.py
ainative/zerodb/tables.py
ainative/zerodb/vectors.py
ainative_python-3.1.0.dist-info/METADATA
ainative_python-3.1.0.dist-info/WHEEL
ainative_python-3.1.0.dist-info/entry_points.txt
ainative_python-3.1.0.dist-info/top_level.txt
ainative_python-3.1.0.dist-info/RECORD
